pythonvideoannotator_module_pathmap/__init__.py
pythonvideoannotator_module_pathmap/module.py
pythonvideoannotator_module_pathmap/pathmap_window.py
Python_video_annotator_module_path_map-0.6.16.dist-info/METADATA
Python_video_annotator_module_path_map-0.6.16.dist-info/WHEEL
Python_video_annotator_module_path_map-0.6.16.dist-info/top_level.txt
Python_video_annotator_module_path_map-0.6.16.dist-info/RECORD
